min3d/D3.py
min3d/__init__.py
Min3D-1.0.dist-info/METADATA
Min3D-1.0.dist-info/WHEEL
Min3D-1.0.dist-info/top_level.txt
Min3D-1.0.dist-info/RECORD
