Metadata-Version: 2.1
Name: Min3D
Version: 1.0
Summary: Simple Console 3D Module
Home-page: UNKNOWN
Author: UNKNOWN
Author-email: UNKNOWN
License: UNKNOWN
Platform: UNKNOWN
